rps/__init__.py
rps/report.py
rps_reputation-1.0.7.dist-info/LICENSE
rps_reputation-1.0.7.dist-info/METADATA
rps_reputation-1.0.7.dist-info/WHEEL
rps_reputation-1.0.7.dist-info/top_level.txt
rps_reputation-1.0.7.dist-info/RECORD
